[
    {
        "package": "poddr",
        "url": "https://github.com/jemus42/poddr"
    },
    {
        "package": "jermd",
        "url": "https://github.com/jemus42/jermd"
    },
    {
        "package": "jemisc",
        "url": "https://github.com/jemus42/jemisc"
    },
    {
        "package": "tRakt",
        "url": "https://github.com/jemus42/tRakt"
    },
    {
        "package": "hugo-rstats-pkg-meta",
        "url": "https://github.com/jemus42/hugo-rstats-pkg-meta"
    },
    {
        "package": "discordiar",
        "url": "https://github.com/jemus42/discordiar"
    },
    {
        "package": "speedrunr",
        "url": "https://github.com/jemus42/speedrunr"
    },
    {
        "package": "radarrr",
        "url": "https://github.com/jemus42/radarrr"
    },
    {
        "package": "attrakttv",
        "url": "https://github.com/jemus42/attrakttv"
    },
    {
        "package": "tadaathemes",
        "url": "https://github.com/tadaadata/tadaathemes"
    }
]


hugo-rstats-pkg-meta